cspdevkit/__init__.py
cspdevkit/aip/Ocr.py
cspdevkit/aip/Unst2st.py
cspdevkit/aip/__init__.py
cspdevkit/aip/common/__init__.py
cspdevkit/aip/common/http_client.py
cspdevkit/command/__init__.py
cspdevkit/command/cli.py
cspdevkit/command/cli_all.py
cspdevkit/common/__init__.py
cspdevkit/common/config.py
cspdevkit/common/docker_server.py
cspdevkit/common/http_client.py
cspdevkit/common/utils.py
cspdevkit/common/config/docker_dict.yaml
cspdevkit/common/config/interface.yaml
cspdevkit/dataset/__init__.py
cspdevkit/dataset/dataset_cli.py
cspdevkit/dataset/dataset_server.py
cspdevkit/datatool/APIs.py
cspdevkit/datatool/__init__.py
cspdevkit/datatool/datatool_cli.py
cspdevkit/datatool/utils.py
cspdevkit/datatool/dataset/__init__.py
cspdevkit/datatool/dataset/dataset.py
cspdevkit/datatool/image_classifier/__init__.py
cspdevkit/datatool/image_detection/__init__.py
cspdevkit/datatool/image_detection/aug.py
cspdevkit/datatool/image_detection/bg_changed.py
cspdevkit/datatool/image_detection/check.py
cspdevkit/datatool/image_detection/eda.py
cspdevkit/datatool/image_detection/eva.py
cspdevkit/datatool/image_detection/split.py
cspdevkit/datatool/image_detection/transform.py
cspdevkit/datatool/image_detection/utils.py
cspdevkit/datatool/image_detection/voc_xml.py
cspdevkit/datatool/text_classifier/__init__.py
cspdevkit/datatool/text_entity/__init__.py
cspdevkit/datatool/text_entity/check.py
cspdevkit/datatool/text_entity/eva.py
cspdevkit/datatool/text_entity/split.py
cspdevkit/datatool/text_entity/text_entity_cli.py
cspdevkit/resources/__init__.py
cspdevkit/resources/resources_cli.py
cspdevkit/resources/resources_server.py
cspdevkit/thirdparty/__init__.py
cspdevkit/thirdparty/ocr/Ocr.py
cspdevkit/thirdparty/ocr/__init__.py
cspdevkit/thirdparty/ocr/ocr_cli.py
cspdevkit/thirdparty/unst2st/Unst2st.py
cspdevkit/thirdparty/unst2st/__init__.py
cspdevkit/thirdparty/unst2st/unst2st_cli.py
cspdevkit_beta-0.1.11.dist-info/METADATA
cspdevkit_beta-0.1.11.dist-info/WHEEL
cspdevkit_beta-0.1.11.dist-info/entry_points.txt
cspdevkit_beta-0.1.11.dist-info/top_level.txt
cspdevkit_beta-0.1.11.dist-info/RECORD
