Metadata-Version: 2.1
Name: cspdevkit-beta
Version: 0.1.11
Summary: UNKNOWN
Home-page: UNKNOWN
License: UNKNOWN
Platform: UNKNOWN
Classifier: Development Status :: 4 - Beta
Classifier: Intended Audience :: Developers
Classifier: Topic :: Software Development :: Build Tools
Classifier: License :: OSI Approved :: MIT License
Classifier: Programming Language :: Python :: 3
Classifier: Programming Language :: Python :: 3.7
Requires-Dist: Click
Requires-Dist: requests
Requires-Dist: PyYAML (==5.4.1)
Requires-Dist: tqdm
Requires-Dist: scipy (==1.7.3)
Requires-Dist: chardet (==3.0.4)
Requires-Dist: prettytable
Requires-Dist: Pillow (==9.1.0)
Requires-Dist: numpy (==1.21.5)
Requires-Dist: matplotlib (==3.5.1)
Requires-Dist: pandas (==1.3.4)
Requires-Dist: lxml
Requires-Dist: openpyxl
Requires-Dist: zipp (==3.7.0)
Requires-Dist: loguru
